[
    {
      "rest_id": "rest_001",
      "rest_name": "Seoul Garden BBQ",
      "distance": "1.1 км",
      "schedule": "Өнөөдөр: 10:00–22:00",
      "address": "СБД, 7-р хороо, Сөүлийн гудамж 14",
      "rank": 4.6,
      "amount_of_people_ranked": 289,
      "category": "korean",
      "restriction": "no restriction"
    },
    {
      "rest_id": "rest_002",
      "rest_name": "Tokyo Ramen House",
      "distance": "850 м",
      "schedule": "Өнөөдөр: 11:00–23:00",
      "address": "БГД, 3-р хороо, Ард Аюушийн гудамж 21",
      "rank": 4.5,
      "amount_of_people_ranked": 198,
      "category": "japanese",
      "restriction": "contains gluten"
    },
    {
      "rest_id": "rest_003",
      "rest_name": "Burger Club",
      "distance": "2.0 км",
      "schedule": "Өнөөдөр: 09:00–21:00",
      "address": "ЧД, 5-р хороо, Барилгачдын гудамж 12",
      "rank": 4.2,
      "amount_of_people_ranked": 127,
      "category": "fastfood",
      "restriction": "no restriction"
    },
    {
      "rest_id": "rest_004",
      "rest_name": "Nomads Mongolian Cuisine",
      "distance": "3.4 км",
      "schedule": "Өнөөдөр: 12:00–23:00",
      "address": "СБД, 11-р хороо, Чингисийн өргөн чөлөө 17",
      "rank": 4.7,
      "amount_of_people_ranked": 420,
      "category": "mongolian",
      "restriction": "vegetarian options"
    },
    {
      "rest_id": "rest_005",
      "rest_name": "Hotpot Dynasty",
      "distance": "1.5 км",
      "schedule": "Өнөөдөр: 11:30–23:00",
      "address": "БЗД, 15-р хороо, Жуковын өргөн чөлөө 8",
      "rank": 4.8,
      "amount_of_people_ranked": 342,
      "category": "chinese",
      "restriction": "contains seafood"
    },
    {
      "rest_id": "rest_006",
      "rest_name": "Italiano Trattoria",
      "distance": "4.2 км",
      "schedule": "Өнөөдөр: 10:00–22:30",
      "address": "ХУД, 11-р хороо, Зайсангийн гудамж 23",
      "rank": 4.4,
      "amount_of_people_ranked": 201,
      "category": "italian",
      "restriction": "contains dairy"
    },
    {
      "rest_id": "rest_007",
      "rest_name": "Urban Coffee Lab",
      "distance": "600 м",
      "schedule": "Өнөөдөр: 08:00–20:00",
      "address": "СБД, 6-р хороо, Сэнтрал Тауэр 1 давхар",
      "rank": 4.5,
      "amount_of_people_ranked": 320,
      "category": "drinks",
      "restriction": "no alcohol"
    },
    {
      "rest_id": "rest_008",
      "rest_name": "Momo Dumpling House",
      "distance": "1.8 км",
      "schedule": "Өнөөдөр: 09:00–21:00",
      "address": "БГД, 10-р хороо, 3-р хороолол 23-р байр",
      "rank": 4.1,
      "amount_of_people_ranked": 147,
      "category": "mongolian",
      "restriction": "contains gluten"
    },
    {
      "rest_id": "rest_009",
      "rest_name": "Sakura Sushi & Rolls",
      "distance": "2.5 км",
      "schedule": "Өнөөдөр: 10:30–22:00",
      "address": "СБД, 8-р хороо, Олимп плаза 3 давхар",
      "rank": 4.9,
      "amount_of_people_ranked": 560,
      "category": "japanese",
      "restriction": "contains seafood"
    },
    {
      "rest_id": "rest_010",
      "rest_name": "BBQ SmokeHouse",
      "distance": "3.9 км",
      "schedule": "Өнөөдөр: 11:30–22:00",
      "address": "ХУД, 15-р хороо, Ривер Гарден 302",
      "rank": 4.3,
      "amount_of_people_ranked": 176,
      "category": "fastfood",
      "restriction": "no restriction"
    },
    {
      "rest_id": "rest_011",
      "rest_name": "Seoul Street Snacks",
      "distance": "1.4 км",
      "schedule": "Өнөөдөр: 10:00–22:00",
      "address": "БЗД, 4-р хороо, Их тойруу 55",
      "rank": 4.2,
      "amount_of_people_ranked": 113,
      "category": "korean",
      "restriction": "spicy foods"
    },
    {
      "rest_id": "rest_012",
      "rest_name": "Pho 99 Vietnamese Kitchen",
      "distance": "900 м",
      "schedule": "Өнөөдөр: 09:00–21:30",
      "address": "ЧД, 4-р хороо, Жуулчны гудамж 38",
      "rank": 4.7,
      "amount_of_people_ranked": 378,
      "category": "chinese",
      "restriction": "contains seafood"
    },
    {
      "rest_id": "rest_013",
      "rest_name": "Mediterranean Olive",
      "distance": "2.6 км",
      "schedule": "Өнөөдөр: 10:00–22:00",
      "address": "СБД, 8-р хороо, Олимп плаза 4 давхар",
      "rank": 2.6,
      "amount_of_people_ranked": 212,
      "category": "italian",
      "restriction": "vegetarian options"
    },
    {
      "rest_id": "rest_014",
      "rest_name": "Taco Fiesta",
      "distance": "3.2 км",
      "schedule": "Өнөөдөр: 11:00–22:00",
      "address": "БГД, 6-р хороо, 21-р байр",
      "rank": 2.3,
      "amount_of_people_ranked": 155,
      "category": "fastfood",
      "restriction": "spicy foods"
    },
    {
      "rest_id": "rest_015",
      "rest_name": "Korean Kimchi House",
      "distance": "1.0 км",
      "schedule": "Өнөөдөр: 10:00–21:30",
      "address": "СБД, 3-р хороо, Сөүлийн гудамж 19",
      "rank": 4.5,
      "amount_of_people_ranked": 234,
      "category": "korean",
      "restriction": "contains seafood"
    },
    {
      "rest_id": "rest_016",
      "rest_name": "Tokyo Bento Café",
      "distance": "1.7 км",
      "schedule": "Өнөөдөр: 09:30–20:30",
      "address": "БЗД, 1-р хороо, 13-р хороолол 24-р байр",
      "rank": 2.1,
      "amount_of_people_ranked": 128,
      "category": "japanese",
      "restriction": "contains egg"
    },
    {
      "rest_id": "rest_017",
      "rest_name": "Steakhouse Prime Cut",
      "distance": "3.8 км",
      "schedule": "Өнөөдөр: 12:00–23:00",
      "address": "ХУД, 4-р хороо, Оргил Шилтгээн 107",
      "rank": 3.8,
      "amount_of_people_ranked": 402,
      "category": "fastfood",
      "restriction": "no restriction"
    },
    {
      "rest_id": "rest_018",
      "rest_name": "Thai Chili Corner",
      "distance": "2.9 км",
      "schedule": "Өнөөдөр: 11:00–22:30",
      "address": "СБД, 2-р хороо, Номин оффис 2 давхар",
      "rank": 1.4,
      "amount_of_people_ranked": 209,
      "category": "chinese",
      "restriction": "spicy foods"
    },
    {
      "rest_id": "rest_019",
      "rest_name": "Greek Taverna",
      "distance": "3.5 км",
      "schedule": "Өнөөдөр: 10:00–22:00",
      "address": "СБД, 9-р хороо, Хүннү гудамж 12",
      "rank": 2.3,
      "amount_of_people_ranked": 164,
      "category": "italian",
      "restriction": "vegetarian options"
    },
    {
      "rest_id": "rest_020",
      "rest_name": "Dragon Wok",
      "distance": "1.6 км",
      "schedule": "Өнөөдөр: 11:00–21:30",
      "address": "БГД, 5-р хороо, 4-р хороолол 7-р байр",
      "rank": 3.2,
      "amount_of_people_ranked": 121,
      "category": "chinese",
      "restriction": "contains gluten"
    }
  ]
  